setup.cfg
setup.py
perform_eda/__init__.py
perform_eda/perform_eda.py
perform_eda.egg-info/PKG-INFO
perform_eda.egg-info/SOURCES.txt
perform_eda.egg-info/dependency_links.txt
perform_eda.egg-info/not-zip-safe
perform_eda.egg-info/top_level.txt