Metadata-Version: 2.1
Name: perform-eda
Version: 0.1.1
Summary: The perform_eda function is used to conduct Exploratory Data Analysis (EDA) on a given dataset. It provides various insights and visualizations to help understand the data.
Author-email: ranjitmaity95@gmail.com
